pysudoku/__init__.py
spydoku-0.0.1.dist-info/LICENSE
spydoku-0.0.1.dist-info/METADATA
spydoku-0.0.1.dist-info/WHEEL
spydoku-0.0.1.dist-info/top_level.txt
spydoku-0.0.1.dist-info/RECORD
