Metadata-Version: 2.1
Name: spydoku
Version: 0.0.1
Summary: Python sudoku generator and solver
Home-page: https://github.com/skopru/pysudoku
Author: Selcuk Kopru
Author-email: selcuk.kopru@gmail.com
License: UNKNOWN
Platform: UNKNOWN
Classifier: Programming Language :: Python :: 3
Classifier: License :: OSI Approved :: MIT License
Classifier: Operating System :: OS Independent
Requires-Python: >=3.6
